scrapwithgpt/__init__.py
scrapwithgpt/config.py
scrapwithgpt/oai.py
scrapwithgpt/prompts.py
scrapwithgpt/scrap.py
scrapwithgpt/utils.py
scrapwithgpt/web.py
scrapwithgpt-0.1.6.dist-info/METADATA
scrapwithgpt-0.1.6.dist-info/WHEEL
scrapwithgpt-0.1.6.dist-info/top_level.txt
scrapwithgpt-0.1.6.dist-info/RECORD
