Metadata-Version: 2.1
Name: scrapwithgpt
Version: 0.1.6
Home-page: https://github.com/HenryObj/scrapwithgpt
Requires-Dist: openai >=1.9.0
Requires-Dist: tiktoken >=0.5.2
Requires-Dist: requests >=2.31.0
Requires-Dist: bs4
